<?xml version="1.0" encoding="iso-8859-1"?><!-- ****************************************************************************************© 2002-2004 PMB Services / www.sigb.net pmb@sigb.net et contributeurs (voir www.sigb.net)****************************************************************************************$Id: oeuvre_link.xml,v 1.2 2015-11-17 17:06:57 apetithomme Exp $ --><XMLlist><entry code="a" inverseof="b" sens="up" expression="yes">Lien a</entry> <entry code="b" inverseof="a" sens="down">Lien b</entry><entry code="c" expression="yes">Lien c</entry><entry code="d" expression="yes">Lien d</entry></XMLlist>